[{
		"Camera": {
            "Front": [-0.0, 0.0, -1.0],
            "Up": [0.0, 1.0, 0.0],
            "Position": [0.0, 0.0, -50.0],
            "Ambient": [0.2, 0.2, 0.2],
            "Diffuse": [0.5, 0.5, 0.5],
            "Specular": [1.0, 1.0, 1.0]
        },
        "Objects": [{
                "Name": "Light5",
                "Position": [0.0, -0.1, -46.0],
                "Rotation": [0.0, 0.0, 0.0],
                "Scale": [0.0, 0.0, 0.0],
                "Shiness": 0.6,
                "Ambient": [0.2, 0.2, 0.2],
                "Diffuse": [0.5, 0.5, 0.5],
                "Specular": [2.0, 2.0, 2.0],
                "FaceSize": 36,
                "ProgramID": 0,
                "VAOID": 0,
				"Type": 1,
				"Attenuation": [0.07, 0.017]
            },{
                "Name": "Light",
                "Position": [3.0, 3.0, -1.0],
                "Rotation": [0.0, 0.0, 0.0],
                "Scale": [0.2, 0.2, 0.2],
                "Shiness": 0.6,
                "Ambient": [1.0, 1.0, 1.0],
                "Diffuse": [1.0, 1.0, 1.0],
                "Specular": [1.0, 1.0, 1.0],
                "FaceSize": 36,
                "ProgramID": 0,
                "VAOID": 0,
				"Type": 0
            },{
                "Name": "Lantern2",
                "Position": [0.0, -0.99, -46.0],
                "Rotation": [0.0, 0.0, 0.0],
                "Scale": [5.0, 5.0, 5.0],
                "Shiness": 0.6,
                "Ambient": [0.0215, 0.1745, 0.0215],
                "Diffuse": [0.07568, 0.61422, 0.07568],
                "Specular": [0.633, 0.72781, 0.633],
                "FaceSize": 36,
                "ProgramID": 16,
                "VAOID": 2,
				"Model": "Lantern_01_1k.gltf"
            },{
                "Name": "Marble",
                "Position": [0.0, -1.0, -55.0],
                "Rotation": [90.0, 0.0, 0.0],
                "Scale": [3.0, 3.0, 3.0],
                "Shiness": 0.6,
                "Ambient": [0.0215, 0.1745, 0.0215],
                "Diffuse": [0.07568, 0.61422, 0.07568],
                "Specular": [0.633, 0.72781, 0.633],
                "FaceSize": 36,
                "ProgramID": 19,
                "VAOID": 2,
				"Model": "marble_bust_01_1k.gltf"
            },{
                "Name": "2Wall",
                "Position" : [4.00000, 1.00000, -46.35000],
                "Rotation" : [0.00000, -135.00000, 0.00000],
                "Scale" : [8.00000, 5.00000, 8.00000],
                "Shiness" : 0.25000,
                "Ambient" : [0.02150, 0.17450, 0.02150],
                "Diffuse" : [0.07568, 0.61422, 0.07568],
                "Specular" : [0.63300, 0.72781, 0.63300],
                "FaceSize" : 36,
                "ProgramID" : 11,
                "VAOID" : 1,
                "Texture" : [10, 11, 12],
                "Type" : 2
            },{
                "Name": "2Floor",
                "Position": [0.0, -1.0, -50.5],
                "Rotation": [-90.0, 0.0, 0.0],
                "Scale": [14.0, 14.0, 5.0],
                "Shiness": 0.25,
                "Ambient": [0.0215, 0.1745, 0.0215],
                "Diffuse": [0.07568, 0.61422, 0.07568],
                "Specular": [0.633, 0.72781, 0.633],
                "FaceSize": 36,
                "ProgramID": 11,
                "VAOID": 1,
				"Texture": [13, 14, 15],
				"Type": 2
            },{
                "Name": "2Floor",
                "Position" : [0.0, 3.0, -50.5],
                "Rotation" : [90.00000, 0.00000, 0.00000],
                "Scale" : [14.00000, 14.0, 5.00000],
                "Shiness" : 0.25000,
                "Ambient" : [0.02150, 0.17450, 0.02150],
                "Diffuse" : [0.07568, 0.61422, 0.07568],
                "Specular" : [0.63300, 0.72781, 0.63300],
                "FaceSize" : 36,
                "ProgramID" : 11,
                "VAOID" : 1,
                "Texture" : [13, 14, 15],
                "Type" : 2
            },{
                "Name": "2Wall",
                "Position": [-4, 1.0, -46.35],
                "Rotation": [0.0, 135.0, 0.0],
                "Scale": [8.0, 5.0, 8.0],
                "Shiness": 0.25,
                "Ambient": [0.0215, 0.1745, 0.0215],
                "Diffuse": [0.07568, 0.61422, 0.07568],
                "Specular": [0.633, 0.72781, 0.633],
                "FaceSize": 36,
                "ProgramID": 11,
                "VAOID": 1,
				"Texture": [10, 11, 12],
				"Type": 2
            },{
                "Name": "2Wall",
                "Position": [0.0, 1.0, -43.5],
                "Rotation": [0.0, -180.0, 0.0],
                "Scale": [5.0, 5.0, 5.0],
                "Shiness": 0.25,
                "Ambient": [0.0215, 0.1745, 0.0215],
                "Diffuse": [0.07568, 0.61422, 0.07568],
                "Specular": [0.633, 0.72781, 0.633],
                "FaceSize": 36,
                "ProgramID": 11,
                "VAOID": 1,
				"Texture": [10, 11, 12],
				"Type": 2
            },{
                "Name": "2Wall",
                "Position" : [6.75000, 1.00000, -53.00000],
                "Rotation" : [0.00000, -90.00000, 0.00000],
                "Scale" : [8.00000, 5.00000, 8.00000],
                "Shiness" : 0.25000,
                "Ambient" : [0.02150, 0.17450, 0.02150],
                "Diffuse" : [0.07568, 0.61422, 0.07568],
                "Specular" : [0.63300, 0.72781, 0.63300],
                "FaceSize" : 36,
                "ProgramID" : 11,
                "VAOID" : 1,
                "Texture" : [],
                "Type" : 2
            },{
                "Name": "2Wall",
                "Position" : [-6.75000, 1.00000, -53.00000],
                "Rotation" : [0.00000, 90.00000, 0.00000],
                "Scale" : [8.00000, 5.00000, 8.00000],
                "Shiness" : 0.25000,
                "Ambient" : [0.02150, 0.17450, 0.02150],
                "Diffuse" : [0.07568, 0.61422, 0.07568],
                "Specular" : [0.63300, 0.72781, 0.63300],
                "FaceSize" : 36,
                "ProgramID" : 11,
                "VAOID" : 1,
                "Texture" : [],
                "Type" : 2
            },{
                "Name": "2Wall",
                "Position" : [0.00000, 1.00000, -57.00000],
                "Rotation" : [0.00000, 0.00000, 0.00000],
                "Scale" : [20.00000, 20.00000, 5.00000],
                "Shiness" : 0.25000,
                "Ambient" : [0.02150, 0.17450, 0.02150],
                "Diffuse" : [0.07568, 0.61422, 0.07568],
                "Specular" : [0.63300, 0.72781, 0.63300],
                "FaceSize" : 36,
                "ProgramID" : 11,
                "VAOID" : 1,
                "Texture" : [10, 11, 12],
                "Type" : 2
            }]
	}]